graphlit/__init__.py
graphlit/graphlit.py
graphlit_api/__init__.py
graphlit_api/add_contents_to_collections.py
graphlit_api/approve_content.py
graphlit_api/ask_graphlit.py
graphlit_api/async_base_client.py
graphlit_api/base_model.py
graphlit_api/branch_conversation.py
graphlit_api/clear_conversation.py
graphlit_api/client.py
graphlit_api/close_conversation.py
graphlit_api/complete_conversation.py
graphlit_api/continue_conversation.py
graphlit_api/count_alerts.py
graphlit_api/count_categories.py
graphlit_api/count_collections.py
graphlit_api/count_connectors.py
graphlit_api/count_contents.py
graphlit_api/count_conversations.py
graphlit_api/count_events.py
graphlit_api/count_facts.py
graphlit_api/count_feeds.py
graphlit_api/count_investment_funds.py
graphlit_api/count_investments.py
graphlit_api/count_labels.py
graphlit_api/count_medical_conditions.py
graphlit_api/count_medical_contraindications.py
graphlit_api/count_medical_devices.py
graphlit_api/count_medical_drug_classes.py
graphlit_api/count_medical_drugs.py
graphlit_api/count_medical_guidelines.py
graphlit_api/count_medical_indications.py
graphlit_api/count_medical_procedures.py
graphlit_api/count_medical_studies.py
graphlit_api/count_medical_tests.py
graphlit_api/count_medical_therapies.py
graphlit_api/count_organizations.py
graphlit_api/count_persons.py
graphlit_api/count_places.py
graphlit_api/count_products.py
graphlit_api/count_repos.py
graphlit_api/count_softwares.py
graphlit_api/count_specifications.py
graphlit_api/count_users.py
graphlit_api/count_views.py
graphlit_api/count_workflows.py
graphlit_api/create_alert.py
graphlit_api/create_category.py
graphlit_api/create_collection.py
graphlit_api/create_connector.py
graphlit_api/create_conversation.py
graphlit_api/create_event.py
graphlit_api/create_fact.py
graphlit_api/create_feed.py
graphlit_api/create_investment.py
graphlit_api/create_investment_fund.py
graphlit_api/create_label.py
graphlit_api/create_medical_condition.py
graphlit_client-1.0.20260131001.dist-info/licenses/LICENSE
graphlit_client-1.0.20260131001.dist-info/METADATA
graphlit_client-1.0.20260131001.dist-info/WHEEL
graphlit_client-1.0.20260131001.dist-info/top_level.txt
graphlit_client-1.0.20260131001.dist-info/RECORD
