Metadata-Version: 2.4
Name: graphlit-client
Version: 1.0.20260131001
Summary: Graphlit API Python Client
Home-page: https://github.com/graphlit/graphlit-client-python
Author: Unstruk Data Inc.
Author-email: questions@graphlit.com
Requires-Python: >=3.6
License-File: LICENSE
Requires-Dist: httpx
Requires-Dist: pydantic<3.0.0,>=2.0.0
Requires-Dist: PyJWT
Requires-Dist: websockets
Dynamic: author
Dynamic: author-email
Dynamic: description
Dynamic: description-content-type
Dynamic: home-page
Dynamic: license-file
Dynamic: requires-dist
Dynamic: requires-python
Dynamic: summary
